{
  "region_name": "United States - Los Angeles",
  "google_module": {
    "base_lat": 34.0522,
    "base_lon": -118.2437,
    "lang_params": "hl=en&gl=US",
    "valid_url_suffix": "com"
  },
  "trust_module": {
    "white_urls": [
      "https://www.amazon.com/",
      "https://en.wikipedia.org/wiki/Special:Random?r=97531",
      "https://en.wikipedia.org/wiki/Special:Random?r=3870",
      "https://en.wikipedia.org/wiki/Special:Random?r=5941",
      "https://en.wikipedia.org/wiki/Special:Random?r=54409",
      "https://en.wikipedia.org/wiki/Special:Random?r=29151",
      "https://www.irs.gov/",
      "https://en.wikipedia.org/wiki/Special:Random?r=86309",
      "https://en.wikipedia.org/wiki/Special:Random?r=35004",
      "https://en.wikipedia.org/wiki/Special:Random?r=56218",
      "https://www.cdc.gov/",
      "https://en.wikipedia.org/wiki/Special:Random?r=64648",
      "https://en.wikipedia.org/wiki/Special:Random?r=66700",
      "https://www.walmart.com/",
      "https://en.wikipedia.org/wiki/Special:Random?r=10184",
      "https://en.wikipedia.org/wiki/Special:Random?r=22926",
      "https://en.wikipedia.org/wiki/Special:Random?r=50276",
      "https://en.wikipedia.org/wiki/Special:Random?r=58496",
      "https://en.wikipedia.org/wiki/Special:Random?r=45525",
      "https://en.wikipedia.org/wiki/Special:Random?r=68403",
      "https://en.wikipedia.org/wiki/Special:Random?r=15410",
      "https://en.wikipedia.org/wiki/Special:Random?r=81230",
      "https://en.wikipedia.org/wiki/Special:Random?r=83468",
      "https://en.wikipedia.org/wiki/Special:Random?r=1309",
      "https://en.wikipedia.org/wiki/Special:Random?r=80738",
      "https://www.chase.com/",
      "https://en.wikipedia.org/wiki/Special:Random?r=49250",
      "https://en.wikipedia.org/wiki/Special:Random?r=28893",
      "https://en.wikipedia.org/wiki/Special:Random?r=88107",
      "https://en.wikipedia.org/wiki/Special:Random?r=21433"
    ],
    "static_urls": [
      "https://www.usps.com/",
      "https://www.amazon.com/",
      "https://www.cdc.gov/",
      "https://www.bankofamerica.com/",
      "https://www.usa.gov/",
      "https://www.chase.com/",
      "https://www.walmart.com/",
      "https://www.target.com/",
      "https://www.harvard.edu/",
      "https://www.irs.gov/"
    ]
  }
}